breathe_plus-0.1.0a2.dist-info/METADATA
breathe_plus-0.1.0a2.dist-info/WHEEL
breathe_plus-0.1.0a2.dist-info/license_files/LICENSE.md
breathe_plus/__init__.py
breathe_plus/backend.cpython-310-x86_64-linux-gnu.so
breathe_plus-0.1.0a2.dist-info/RECORD
