Metadata-Version: 2.1
Name: breathe_plus
Version: 0.1.0a2
Requires-Dist: docutils>=0.12
Requires-Dist: Sphinx>=4.0,<6,!=5.0.0
License-File: LICENSE.md
Summary: Integrate your doxygen-generated technical documentation into Sphinx
Author: Michael Jones
Project-URL: repository, https://github.com/breathe-doc/breathe-plus
